hookx/__init__.py
hookx/cli/__init__.py
hookx/cli/commands.py
hookx/cli/main.py
hookx/core/__init__.py
hookx/core/analyzer.py
hookx/core/api.py
hookx/core/models.py
hookx/core/reporter.py
hookx/core/scanner.py
hookx/utils/__init__.py
hookx/utils/frappe_utils.py
hookx/utils/paths.py
hookx/utils/performance.py
hookx/utils/validation.py
hookx-1.0.2.dist-info/licenses/LICENSE
tests/__init__.py
tests/test_scanner.py
hookx-1.0.2.dist-info/METADATA
hookx-1.0.2.dist-info/WHEEL
hookx-1.0.2.dist-info/entry_points.txt
hookx-1.0.2.dist-info/top_level.txt
hookx-1.0.2.dist-info/RECORD
